cyrandom/__init__.pxd
cyrandom/__init__.py
cyrandom/cyrandom.cpython-35m-darwin.so
cyrandom/cyrandom.pxd
cyrandom-0.3.0.dist-info/DESCRIPTION.rst
cyrandom-0.3.0.dist-info/METADATA
cyrandom-0.3.0.dist-info/RECORD
cyrandom-0.3.0.dist-info/WHEEL
cyrandom-0.3.0.dist-info/metadata.json
cyrandom-0.3.0.dist-info/top_level.txt
