Metadata-Version: 2.0
Name: cyrandom
Version: 0.3.0
Summary: Fast random number generation.
Home-page: https://github.com/Noctem/cyrandom
Author: David Christenson
Author-email: mail@noctem.xyz
License: MIT
Keywords: cyrandom random rng cython
Platform: UNKNOWN
Classifier: Development Status :: 4 - Beta
Classifier: Intended Audience :: Developers
Classifier: Programming Language :: C
Classifier: Programming Language :: Cython
Classifier: Programming Language :: Python :: 3
Classifier: Programming Language :: Python :: 3 :: Only
Classifier: Programming Language :: Python :: 3.5
Classifier: Programming Language :: Python :: 3.6
Classifier: License :: OSI Approved :: MIT License
